PyWSGIRef/__init__.py
PyWSGIRef/__main__.py
PyWSGIRef/beta.py
PyWSGIRef/commons.py
PyWSGIRef/defaults.py
PyWSGIRef/exceptions.py
PyWSGIRef/finished.py
PyWSGIRef/loadContent.py
PyWSGIRef/patterns.py
PyWSGIRef/pyhtml.py
PyWSGIRef/simpleServer.py
PyWSGIRef/stats.py
PyWSGIRef/templateDict.py
pywsgiref-1.1.18.dist-info/licenses/LICENSE
pywsgiref-1.1.18.dist-info/METADATA
pywsgiref-1.1.18.dist-info/WHEEL
pywsgiref-1.1.18.dist-info/top_level.txt
pywsgiref-1.1.18.dist-info/RECORD
