Metadata-Version: 2.4
Name: PyWSGIRef
Version: 1.1.18
Summary: easy server-setup
Author-email: Leander Kafemann <leander.kafemann+python@icloud.com>
Project-URL: Homepage, https://github.com/LeanderKafemann/PyWSGIRef
Classifier: Programming Language :: Python :: 3
Classifier: License :: OSI Approved :: MIT License
Classifier: Operating System :: OS Independent
Requires-Python: >=3.11
License-File: LICENSE
Requires-Dist: requests
Requires-Dist: legacy-cgi
Requires-Dist: naturalsize
Dynamic: license-file
